{
  "CallLogDetails.xaml": [
    {
      "CreatedDate": "Mar 13 4:00 PM",
      "FullName": "firstnametest lastnametest",
      "CallDuration": "00:54:89",
      "CallInfoId": "JAJA45"
    },
    {
      "CreatedDate": "Mar 13 4:00 PM",
      "FullName": "Khadeeja Alif",
      "CallDuration": "00:54:89",
      "CallInfoId": "JAJA45"
    },
    {
      "CreatedDate": "Mar 13 4:00 PM",
      "FullName": "Khadeeja Alif",
      "CallDuration": "00:54:89",
      "CallInfoId": "JAJA45"
    },
    {
      "CreatedDate": "Mar 13 4:00 PM",
      "FullName": "Khadeeja Alif",
      "CallDuration": "00:54:89",
      "CallInfoId": "JAJA45"
    }
  ]
}
